[
  {
    "id": 1,
    "name": "Aarav Patel",
    "email": "aaravpatel@example.com",
    "hashedPassword": "$2b$10$H6a/3m89x0nfPU9gJQsXWeeGLOx0Fg5YzYvR/DKOCwE5HlQxZ4I.m"
  },
  {
    "id": 2,
    "name": "Maya Tan",
    "email": "mayatan@example.com",
    "hashedPassword": "$2b$10$8JHw9Jluf2yppQ3F6EvsYu3Nh.LRYETgZJdWObGKt2CkJj6bYzwRu"
  },
  {
    "id": 3,
    "name": "Xian Li",
    "email": "xianli@example.com",
    "hashedPassword": "$2b$10$pYg4Rn.eE7FsL18QXlyGteElI5AZRRU.jx9hHJKFeSlBQkEpEBHnO"
  },
  {
    "id": 4,
    "name": "Omar Al-Farsi",
    "email": "omarfarsi@example.com",
    "hashedPassword": "$2b$10$Q/ZPqEvs.y/YYcEGWQsyEOcHFukm5lIY4mZDTCylB0nVXowcdRIaS"
  },
  {
    "id": 5,
    "name": "Priya Sharma",
    "email": "priyasharma@example.com",
    "hashedPassword": "$2b$10$Ks76X7FbNWnLFp49JKnW/eGeujk/qtn7Wf/RAGnsZ1Y4MvL5dKQYK"
  },
  {
    "id": 6,
    "name": "Siti Aminah",
    "email": "sitiaminah@example.com",
    "hashedPassword": "$2b$10$2nZ8w0t3Mv.DfE5.kLmF9OTRn8VxqkwxgRy5sIU9chp61B69hG5uq"
  },
  {
    "id": 7,
    "name": "Li Mei",
    "email": "limei@example.com",
    "hashedPassword": "$2b$10$B2.Ald1PQe/cXOsmBFPbAu7I8eOL8EULG.D3a1YqsPeMA5xvRcmti"
  },
  {
    "id": 8,
    "name": "Yusuf Al-Mansoor",
    "email": "yusufmansoor@example.com",
    "hashedPassword": "$2b$10$nL7jMVXrk3EF7c/E96ypLO/g8mSa/Rs5xeOFBHQvLdZX5yR1PS2K."
  },
  {
    "id": 9,
    "name": "Nisha Kumar",
    "email": "nishakumar@example.com",
    "hashedPassword": "$2b$10$BShRh4zq/Sezxv1dAv3Kc/Q2ZT1UdjqHHQBBaUCxGnWc8yoQls6Vm"
  },
  {
    "id": 10,
    "name": "Hassan Al-Bashir",
    "email": "hassanbashir@example.com",
    "hashedPassword": "$2b$10$.zhrwhqTcRG8PEuSRtNBrubpJHd.NmYaC4F.BJZo9fyGvPTUXUoG6"
  },
  {
    "id": 11,
    "name": "Ananya Gupta",
    "email": "ananyagupta@example.com",
    "hashedPassword": "$2b$10$yrdbOK/4BrpW1ELMPHV.Tu05ENpFeOVyHBwXe5BMzUtIB8DA.WEVW"
  },
  {
    "id": 12,
    "name": "Farah Nasir",
    "email": "farahnasir@example.com",
    "hashedPassword": "$2b$10$aBT8ED7iyESc5MJjxnv9wuUJ6gnGQdxcn39MVU07o1MZ/FqHtGHnC"
  },
  {
    "id": 13,
    "name": "Zheng Wei",
    "email": "zhengwei@example.com",
    "hashedPassword": "$2b$10$5J0ONEMRtEuDQyCvzXUuKOnOZ7Qxf2E2B0fX2QH7o.NLt2DeVF0pm"
  },
  {
    "id": 14,
    "name": "Rasha Al-Mujahid",
    "email": "rashamujahid@example.com",
    "hashedPassword": "$2b$10$9ScbbMgTqZKaVc/zFn3ZMu9NR7kZlNxv7DdFoHe6.xLDosL6pZYte"
  },
  {
    "id": 15,
    "name": "Arif Aziz",
    "email": "arifaziz@example.com",
    "hashedPassword": "$2b$10$DH52i/BvZBO2EX2kBQ5hye8bP9AeFwi5DELGxOCkaGMMMPbA5G9WG"
  },
  {
    "id": 16,
    "name": "Amina Al-Sayeed",
    "email": "aminaalsayeed@example.com",
    "hashedPassword": "$2b$10$B2.Ald1PQe/cXOsmBFPbAu7I8eOL8EULG.D3a1YqsPeMA5xvRcmti"
  },
  {
    "id": 17,
    "name": "Ravi Singh",
    "email": "ravisingh@example.com",
    "hashedPassword": "$2b$10$BShRh4zq/Sezxv1dAv3Kc/Q2ZT1UdjqHHQBBaUCxGnWc8yoQls6Vm"
  },
  {
    "id": 18,
    "name": "Hua Ying",
    "email": "huaying@example.com",
    "hashedPassword": "$2b$10$H6a/3m89x0nfPU9gJQsXWeeGLOx0Fg5YzYvR/DKOCwE5HlQxZ4I.m"
  },
  {
    "id": 19,
    "name": "Amina Zain",
    "email": "aminazain@example.com",
    "hashedPassword": "$2b$10$8JHw9Jluf2yppQ3F6EvsYu3Nh.LRYETgZJdWObGKt2CkJj6bYzwRu"
  },
  {
    "id": 20,
    "name": "Zainab Khan",
    "email": "zainabkhan@example.com",
    "hashedPassword": "$2b$10$pYg4Rn.eE7FsL18QXlyGteElI5AZRRU.jx9hHJKFeSlBQkEpEBHnO"
  },
  {
    "id": 21,
    "name": "Iqbal Rashid",
    "email": "iqbalrashid@example.com",
    "hashedPassword": "$2b$10$Q/ZPqEvs.y/YYcEGWQsyEOcHFukm5lIY4mZDTCylB0nVXowcdRIaS"
  },
  {
    "id": 22,
    "name": "Lina Tan",
    "email": "linatan@example.com",
    "hashedPassword": "$2b$10$Ks76X7FbNWnLFp49JKnW/eGeujk/qtn7Wf/RAGnsZ1Y4MvL5dKQYK"
  },
  {
    "id": 23,
    "name": "Imran Ahmed",
    "email": "imranahmed@example.com",
    "hashedPassword": "$2b$10$2nZ8w0t3Mv.DfE5.kLmF9OTRn8VxqkwxgRy5sIU9chp61B69hG5uq"
  },
  {
    "id": 24,
    "name": "Ming Wei",
    "email": "mingwei@example.com",
    "hashedPassword": "$2b$10$B2.Ald1PQe/cXOsmBFPbAu7I8eOL8EULG.D3a1YqsPeMA5xvRcmti"
  },
  {
    "id": 25,
    "name": "Fatima Al-Jabari",
    "email": "fatimaaljabari@example.com",
    "hashedPassword": "$2b$10$nL7jMVXrk3EF7c/E96ypLO/g8mSa/Rs5xeOFBHQvLdZX5yR1PS2K."
  },
  {
    "id": 26,
    "name": "Ayesha Banu",
    "email": "ayeshabanu@example.com",
    "hashedPassword": "$2b$10$BShRh4zq/Sezxv1dAv3Kc/Q2ZT1UdjqHHQBBaUCxGnWc8yoQls6Vm"
  },
  {
    "id": 27,
    "name": "Tariq Ibrahim",
    "email": "tariqibrahim@example.com",
    "hashedPassword": "$2b$10$.zhrwhqTcRG8PEuSRtNBrubpJHd.NmYaC4F.BJZo9fyGvPTUXUoG6"
  },
  {
    "id": 28,
    "name": "Liyana Wong",
    "email": "liyanawong@example.com",
    "hashedPassword": "$2b$10$yrdbOK/4BrpW1ELMPHV.Tu05ENpFeOVyHBwXe5BMzUtIB8DA.WEVW"
  },
  {
    "id": 29,
    "name": "Sofia Mohammed",
    "email": "sofiamohammed@example.com",
    "hashedPassword": "$2b$10$aBT8ED7iyESc5MJjxnv9wuUJ6gnGQdxcn39MVU07o1MZ/FqHtGHnC"
  },
  {
    "id": 30,
    "name": "Rajesh Verma",
    "email": "rajeshverma@example.com",
    "hashedPassword": "$2b$10$5J0ONEMRtEuDQyCvzXUuKOnOZ7Qxf2E2B0fX2QH7o.NLt2DeVF0pm"
  }
]
